diskimage/__init__.py
diskimage/__main__.py
diskimage/diskimage.py
diskimage/filesystem.py
diskimage/item.py
diskimage/tests/__init__.py
diskimage/tests/test_diskimage.py
diskimage-0.0.4.dist-info/LICENSE
diskimage-0.0.4.dist-info/METADATA
diskimage-0.0.4.dist-info/WHEEL
diskimage-0.0.4.dist-info/entry_points.txt
diskimage-0.0.4.dist-info/top_level.txt
diskimage-0.0.4.dist-info/RECORD
