Metadata-Version: 2.1
Name: diskimage
Version: 0.0.4
Summary: A tool for easy handling of disk-images
Home-page: https://github.com/jarlethorsen/diskimage
Author: Jarle Thorsen
Author-email: jarlethorsen@gmail.com
License: UNKNOWN
Platform: UNKNOWN
Classifier: Programming Language :: Python :: 3
Classifier: License :: OSI Approved :: MIT License
Classifier: Operating System :: OS Independent
Classifier: Development Status :: 3 - Alpha
Requires-Python: >=3.0
Requires-Dist: pytsk3 (>=20210419)
Requires-Dist: libewf-python (>=20201230)
